tril/__init__.py
tril/agent.py
tril/base_algorithm.py
tril/base_metric.py
tril/base_reward.py
tril/base_task.py
tril/logging.py
tril/algorithms/__init__.py
tril/algorithms/aggrevated.py
tril/algorithms/base_online.py
tril/algorithms/base_supervised.py
tril/algorithms/bc.py
tril/algorithms/d2lols.py
tril/algorithms/gail.py
tril/algorithms/lols.py
tril/algorithms/ppo.py
tril/algorithms/ppo_pp.py
tril/buffers/__init__.py
tril/buffers/offline_buffer.py
tril/buffers/online_buffer.py
tril/buffers/prompt_buffer.py
tril/metrics/__init__.py
tril/metrics/automated_metrics.py
tril/metrics/metric_utils.py
tril/metrics/model_metrics.py
tril/metrics/caption_metrics/__init__.py
tril/metrics/caption_metrics/cider.py
tril/metrics/caption_metrics/spacy_preprocess.py
tril/metrics/caption_metrics/spice/__init__.py
tril/metrics/caption_metrics/spice/get_stanford_models.sh
tril/metrics/caption_metrics/spice/parallel_spice.py
tril/metrics/caption_metrics/spice/spice.py
tril/metrics/caption_metrics/spice/lib/stanford-corenlp-full-2015-12-09/corenlp.sh
tril/policies/__init__.py
tril/policies/actor.py
tril/policies/actor_critic.py
tril/policies/critic.py
tril/policies/multi_actor_critic.py
tril/rewards/__init__.py
tril/rewards/automated_rewards.py
tril/rewards/model_rewards.py
tril/tasks/__init__.py
tril/tasks/tasks.py
tril/utils/__init__.py
tril/utils/builders.py
tril/utils/evaluation.py
tril/utils/generation_mixin.py
tril/utils/helpers.py
tril/utils/kl_controller.py
tril/utils/logit_processors.py
tril/utils/policy.py
tril/utils/supervised.py
tril-0.2.1.dist-info/LICENSE
tril-0.2.1.dist-info/METADATA
tril-0.2.1.dist-info/WHEEL
tril-0.2.1.dist-info/top_level.txt
tril-0.2.1.dist-info/RECORD
