Metadata-Version: 2.1
Name: tril
Version: 0.2.1
Summary: Transformers Reinforcement and Imitation Learning Library
Author-email: Jonathan Chang <jdc396@cornell.edu>, Kiante Brantley <kdb82@cornell.edu>
License: MIT License
Project-URL: Homepage, https://github.com/Cornell-RL/tril
Project-URL: Source, https://github.com/Cornell-RL/tril
Keywords: reinforcement learning,imitation learning,machine learning,transformers
Classifier: Development Status :: 3 - Alpha
Classifier: Intended Audience :: Developers
Classifier: Intended Audience :: Science/Research
Classifier: License :: OSI Approved :: MIT License
Classifier: Programming Language :: Python :: 3
Classifier: Programming Language :: Python :: 3.10
Classifier: Programming Language :: Python :: 3.11
Requires-Python: >=3.10
License-File: LICENSE
Requires-Dist: torch >=2.1.0
Requires-Dist: transformers >=4.34
Requires-Dist: accelerate >=0.23
Requires-Dist: peft >=0.6.1
Requires-Dist: bitsandbytes >=0.41.1
Requires-Dist: hydra-core >=1.3
Requires-Dist: deepspeed >=0.10.3
Requires-Dist: spacy >=3.7.0
Requires-Dist: scipy
Requires-Dist: rouge
Requires-Dist: jpype1
Requires-Dist: shortuuid
Requires-Dist: jsonlines
Requires-Dist: rich
Requires-Dist: wandb
Requires-Dist: gem-metrics-fork
Requires-Dist: pre-commit
